Metadata-Version: 2.1
Name: fight
Version: 0.0.0
Summary: Python module for graphics integration vulkan
Home-page: https://github.com/echochel/fight
Author: echochel
Author-email: echochel@bk.ru
License: Apache License, Version 2.0, see LICENSE file
Classifier: License :: OSI Approved :: Apache Software License
Classifier: Operating System :: OS Independent
Classifier: Intended Audience :: End Users/Desktop
Classifier: Intended Audience :: Developers
Classifier: Programming Language :: Python :: 3
Requires-Dist: asyncio
